mopnette/__init__.py
mopnette/mopnette.py
mopnette-0.0.11.dist-info/LICENSE
mopnette-0.0.11.dist-info/METADATA
mopnette-0.0.11.dist-info/WHEEL
mopnette-0.0.11.dist-info/top_level.txt
mopnette-0.0.11.dist-info/RECORD
